anywidget_aggrid/__init__.py
anywidget_aggrid/ag_grid_widget.py
anywidget_aggrid/dist/index.js
anywidget_aggrid-0.1.0.dist-info/METADATA
anywidget_aggrid-0.1.0.dist-info/WHEEL
anywidget_aggrid-0.1.0.dist-info/RECORD
