Metadata-Version: 2.4
Name: anywidget-aggrid
Version: 0.1.0
Summary: An AnyWidget wrapper around AG Grid
Author: barnab
Author-email: bittnerbarni@gmail.com
Requires-Python: >=3.12
Classifier: Programming Language :: Python :: 3
Classifier: Programming Language :: Python :: 3.12
Classifier: Programming Language :: Python :: 3.13
Classifier: Programming Language :: Python :: 3.14
Requires-Dist: anywidget (>=0.9.18,<0.10.0)
